knxsonos-0.1.0.dist-info/DESCRIPTION.rst
knxsonos-0.1.0.dist-info/WHEEL
knxsonos-0.1.0.dist-info/METADATA
knxsonos-0.1.0.dist-info/metadata.json
knxsonos-0.1.0.dist-info/entry_points.txt
knxsonos-0.1.0.dist-info/top_level.txt
knxsonos-0.1.0.dist-info/RECORD
knxsonos/__init__.py
knxsonos/sonos.py
knxsonos/EIBConnection.py
knxsonos/knx.py
knxsonos/__main__.py
knxsonos/knxsonos.py
