Metadata-Version: 2.0
Name: knxsonos
Version: 0.1.0
Summary: Control a Sonos system from your KNX installation
Home-page: https://github.com/TrondKjeldas/knxsonos
Author: Trond Kjeldås
Author-email: trond@kjeldas.no
License: GPL
Keywords: Knx Sonos HomeAutomation
Platform: UNKNOWN
Classifier: Development Status :: 4 - Beta
Classifier: Intended Audience :: End Users/Desktop
Classifier: Intended Audience :: Developers
Classifier: Topic :: Home Automation
Classifier: License :: OSI Approved :: GNU General Public License v3 (GPLv3)
Classifier: Programming Language :: Python :: 2
Classifier: Programming Language :: Python :: 2.6
Classifier: Programming Language :: Python :: 2.7
Requires-Dist: soco
Provides-Extra: test
Requires-Dist: coverage; extra == 'test'
Requires-Dist: mock; extra == 'test'
